calculator/__init__.py
calculator/calc_mod.py
calculator/tests.py
calculator_package_emabaran-0.0.1.dist-info/METADATA
calculator_package_emabaran-0.0.1.dist-info/WHEEL
calculator_package_emabaran-0.0.1.dist-info/top_level.txt
calculator_package_emabaran-0.0.1.dist-info/RECORD
