Metadata-Version: 2.1
Name: calculator-package-emabaran
Version: 0.0.1
Summary: Calculator Python package
Home-page: https://github.com/TuringCollegeSubmissions/ebaran-DWWP.1
Author: Emilija Baranauskaite
Author-email: e.baranauskaite.e@gmail.com
License: BSD 2-clause
Classifier: Development Status :: 1 - Planning
Classifier: Intended Audience :: Science/Research
Classifier: License :: OSI Approved :: BSD License
Classifier: Operating System :: POSIX :: Linux
Classifier: Programming Language :: Python :: 2
Classifier: Programming Language :: Python :: 2.7
Classifier: Programming Language :: Python :: 3
Classifier: Programming Language :: Python :: 3.4
Classifier: Programming Language :: Python :: 3.5
Classifier: Programming Language :: Python :: 3.9
